[
  {
    "button_id": "button.banner_direct_tap",
    "focus_impact": "neutral"
  },
  {
    "button_id": "button.banner_lure_hold",
    "focus_impact": "neutral"
  },
  {
    "button_id": "button.deconstruct",
    "key_id": "key.deconstruct",
    "focus_impact": "neutral",
    "ui_slot": "facebutton_right",
    "ui_label": "key.deconstruct"
  },
  {
    "button_id": "button.rotate_preview_clockwise",
    "focus_impact": "neutral"
  },
  {
    "button_id": "button.rotate_preview_counterclockwise",
    "focus_impact": "neutral"
  }
]