{
  "format_version": "1.8.0",
  "animations": {
    "animation.entity_struct_piglin_crate.open": {
      "anim_time_update": "(query.anim_time + (query.delta_time * 1))",
      "blend_weight": "1",
      "bones": {
        "joint_handle_l": {
          "lod_distance": 0.0,
          "rotation": {
            "0.0": {
              "lerp_mode": "catmullrom",
              "post": [-6.801043526906327e-16,-5.578045476892553e-16,10.061436653137214]
            },
            "0.0333333333333": {
              "lerp_mode": "catmullrom",
              "post": [-5.96133317948104e-17,-7.145233776836379e-17,1.1768627166748118]
            },
            "0.0666666666667": {
              "lerp_mode": "catmullrom",
              "post": [1.2335637272395915e-16,4.809840592083282e-16,-7.707711696624749]
            },
            "0.1": {
              "lerp_mode": "catmullrom",
              "post": [-9.000368809616854e-16,-1.7464338123517166e-15,31.87023353576661]
            },
            "0.133333333333": {
              "lerp_mode": "catmullrom",
              "post": [2.735754212821991e-15,-8.1697183265954e-15,79.90636444091797]
            },
            "0.166666666667": {
              "lerp_mode": "catmullrom",
              "post": [-2.3197475333051974e-15,4.289786079391668e-15,95.18842315673828]
            },
            "0.2": {
              "lerp_mode": "catmullrom",
              "post": [3.2308424293932877e-15,7.539397911863165e-15,107.31417083740234]
            },
            "0.233333333333": {
              "lerp_mode": "catmullrom",
              "post": [-1.6089263778153347e-15,3.3495665906869495e-15,116.45207977294922]
            },
            "0.266666666667": {
              "lerp_mode": "catmullrom",
              "post": [1.3595365847376192e-15,4.5696677880211175e-15,122.77057647705078]
            },
            "0.3": {
              "lerp_mode": "catmullrom",
              "post": [-1.3379190333742685e-15,2.866191357468522e-15,126.43814086914062]
            },
            "0.333333333333": {
              "lerp_mode": "catmullrom",
              "post": [1.5454823395165667e-15,4.2109650049684455e-15,127.62322998046875]
            },
            "0.366666666667": {
              "lerp_mode": "catmullrom",
              "post": [3.8227448177698565e-15,-6.6604119172231175e-15,63.138134002685554]
            },
            "0.4": {
              "lerp_mode": "catmullrom",
              "post": [-5.972683420974248e-17,8.177981344754059e-17,-1.34696972370147]
            },
            "0.433333333333": {
              "lerp_mode": "catmullrom",
              "post": [1.2314292042125106e-16,-4.841514859750273e-16,7.75854682922364]
            },
            "0.466666666667": {
              "lerp_mode": "catmullrom",
              "post": [7.511399237791674e-16,-1.6985504045687206e-15,24.66879081726075]
            },
            "0.5": {
              "lerp_mode": "catmullrom",
              "post": [-3.973304500627835e-15,-9.239118810085876e-16,33.77430725097657]
            },
            "0.533333333333": {
              "lerp_mode": "catmullrom",
              "post": [2.2952056006914513e-15,-2.081247831072094e-15,25.19751930236817]
            },
            "0.566666666667": {
              "lerp_mode": "catmullrom",
              "post": [1.161396520133525e-16,-5.78230800151852e-16,9.269197463989265]
            },
            "0.6": {
              "lerp_mode": "catmullrom",
              "post": [-9.678198455327636e-18,-4.2339917941629446e-17,0.692409873008735]
            },
            "0.633333333333": {
              "lerp_mode": "catmullrom",
              "post": [-6.603231687569294e-16,-2.4508114823327014e-16,4.4160823822021555]
            },
            "0.7": {
              "lerp_mode": "catmullrom",
              "post": [-7.104205089058114e-16,-8.333263659809501e-16,15.055146217346199]
            },
            "0.733333333333": {
              "lerp_mode": "catmullrom",
              "post": [1.0689852255880809e-16,-6.827085554869665e-16,10.948724746704109]
            },
            "0.766666666667": {
              "lerp_mode": "catmullrom",
              "post": [-2.6087132467774755e-16,-1.9593642898247362e-16,3.32251429557801]
            },
            "0.8": {
              "lerp_mode": "catmullrom",
              "post": [3.998080214335023e-17,4.8274720461014843e-17,-0.7839070558547904]
            },
            "0.866666666667": {
              "lerp_mode": "catmullrom",
              "post": [-2.696093165616229e-16,-3.9544810462596845e-16,6.708546638488777]
            },
            "0.933333333333": {
              "lerp_mode": "catmullrom",
              "post": [0.0,0.0,0.0]
            },
            "1.03333333333": {
              "lerp_mode": "catmullrom",
              "post": [0.0,0.0,0.0]
            },
            "1.4": {
              "lerp_mode": "catmullrom",
              "post": [0.0,0.0,0.0]
            },
            "lod_distance": 0.0
          }
        },
        "joint_handle_r": {
          "lod_distance": 0.0,
          "rotation": {
            "0.0": {
              "lerp_mode": "catmullrom",
              "post": [1.8505910634994507,-1.120755910873413,-0.17688460648059845]
            },
            "0.0333333333333": {
              "lerp_mode": "catmullrom",
              "post": [1.8225466012954712,-1.259656548500061,3.272397756576538]
            },
            "0.0666666666667": {
              "lerp_mode": "catmullrom",
              "post": [1.778054118156433,-1.3942177295684814,6.722135066986084]
            },
            "0.1": {
              "lerp_mode": "catmullrom",
              "post": [2.2958686351776123,0.027189869433641434,-32.0455207824707]
            },
            "0.133333333333": {
              "lerp_mode": "catmullrom",
              "post": [1.5390920639038086,1.7442635297775269,-79.93203735351562]
            },
            "0.166666666667": {
              "lerp_mode": "catmullrom",
              "post": [0.9697636961936951,2.1407816410064697,-96.99041748046875]
            },
            "0.2": {
              "lerp_mode": "catmullrom",
              "post": [0.4053121507167816,2.3339061737060547,-111.51321411132812]
            },
            "0.233333333333": {
              "lerp_mode": "catmullrom",
              "post": [-0.07806600630283356,2.3816113471984863,-123.24598693847656]
            },
            "0.266666666667": {
              "lerp_mode": "catmullrom",
              "post": [-0.4387606978416443,2.352426767349243,-131.93629455566406]
            },
            "0.3": {
              "lerp_mode": "catmullrom",
              "post": [-0.659881591796875,2.3072662353515625,-137.3336181640625]
            },
            "0.333333333333": {
              "lerp_mode": "catmullrom",
              "post": [-0.7354583740234375,2.2886199951171875,-139.1882781982422]
            },
            "0.366666666667": {
              "lerp_mode": "catmullrom",
              "post": [0.7797461748123169,2.2761447429656982,-102.45242309570312]
            },
            "0.4": {
              "lerp_mode": "catmullrom",
              "post": [2.4035630226135254,0.12306690961122513,-34.29759216308594]
            },
            "0.433333333333": {
              "lerp_mode": "catmullrom",
              "post": [2.001007318496704,-1.3377156257629395,2.382174253463745]
            },
            "0.466666666667": {
              "lerp_mode": "catmullrom",
              "post": [2.112644910812378,-1.1533080339431763,-2.7503297328948975]
            },
            "0.5": {
              "lerp_mode": "catmullrom",
              "post": [2.2744181156158447,-0.787485659122467,-12.280384063720703]
            },
            "0.533333333333": {
              "lerp_mode": "catmullrom",
              "post": [2.335723638534546,-0.5808327198028564,-17.411191940307617]
            },
            "0.566666666667": {
              "lerp_mode": "catmullrom",
              "post": [2.268174171447754,-0.8053011894226074,-11.831162452697754]
            },
            "0.6": {
              "lerp_mode": "catmullrom",
              "post": [2.0862772464752197,-1.2003620862960815,-1.4665471315383911]
            },
            "0.633333333333": {
              "lerp_mode": "catmullrom",
              "post": [1.9596316814422607,-1.3976373672485352,4.115537166595459]
            },
            "0.666666666667": {
              "lerp_mode": "catmullrom",
              "post": [2.0347790718078613,-1.2857502698898315,0.9069839119911194]
            },
            "0.7": {
              "lerp_mode": "catmullrom",
              "post": [2.1572368144989014,-1.0675452947616577,-5.05101203918457]
            },
            "0.766666666667": {
              "lerp_mode": "catmullrom",
              "post": [2.1578149795532227,-1.066375732421875,-5.082063674926758]
            },
            "0.8": {
              "lerp_mode": "catmullrom",
              "post": [2.0367677211761475,-1.2825969457626343,0.8182507753372192]
            },
            "0.866666666667": {
              "lerp_mode": "catmullrom",
              "post": [2.029010057449341,-1.2948377132415771,1.163190484046936]
            },
            "1.03333333333": {
              "lerp_mode": "catmullrom",
              "post": [2.0558571815490723,-1.2517623901367188,-0.04493078216910362]
            },
            "1.4": {
              "lerp_mode": "catmullrom",
              "post": [2.0558571815490723,-1.2517623901367188,-0.04493078216910362]
            },
            "lod_distance": 0.0
          }
        },
        "joint_lava_m": {
          "lod_distance": 0.0,
          "position": {
            "0.0": {
              "lerp_mode": "catmullrom",
              "post": [-1.3988810110276972e-14,0.0,-4.8790832485323676e-14]
            },
            "0.0333333333333": {
              "lerp_mode": "catmullrom",
              "post": [4.440892098500626e-16,-134.89578247070312,3.833738881908744e-15]
            },
            "0.0666666666667": {
              "lerp_mode": "catmullrom",
              "post": [3.197442310920451e-14,-269.7915725708008,3.0118268989909325e-14]
            },
            "0.166666666667": {
              "lerp_mode": "catmullrom",
              "post": [-8.881784197001252e-15,-269.7915725708008,1.3699111289788846e-14]
            },
            "0.333333333333": {
              "lerp_mode": "catmullrom",
              "post": [0.0,-269.7915725708008,0.0]
            },
            "0.7": {
              "lerp_mode": "catmullrom",
              "post": [0.0,-269.7915725708008,0.0]
            },
            "1.4": {
              "lerp_mode": "catmullrom",
              "post": [0.0,-269.7915725708008,0.0]
            },
            "lod_distance": 0.0
          }
        },
        "joint_lid_m": {
          "lod_distance": 0.0,
          "position": {
            "0.0": {
              "lerp_mode": "catmullrom",
              "post": [-1.3766765505351941e-14,0.0,-5.70168912084057e-14]
            },
            "0.0333333333333": {
              "lerp_mode": "catmullrom",
              "post": [1.3322676295501878e-14,56.65473937988281,-13.895426750183105]
            },
            "0.0666666666667": {
              "lerp_mode": "catmullrom",
              "post": [-7.460698725481052e-14,129.1939239501953,-111.89726257324219]
            },
            "0.1": {
              "lerp_mode": "catmullrom",
              "post": [1.2434497875801753e-14,106.10646057128906,-198.44203186035156]
            },
            "0.133333333333": {
              "lerp_mode": "catmullrom",
              "post": [5.5067062021407764e-14,70.69145202636719,-233.90586853027344]
            },
            "0.166666666667": {
              "lerp_mode": "catmullrom",
              "post": [5.595524044110789e-14,64.3023681640625,-237.88978576660156]
            },
            "0.233333333333": {
              "lerp_mode": "catmullrom",
              "post": [7.771561172376096e-14,61.61222839355469,-239.56723022460938]
            },
            "0.266666666667": {
              "lerp_mode": "catmullrom",
              "post": [4.1022740759899534e-14,74.24299621582031,-229.2130584716797]
            },
            "0.3": {
              "lerp_mode": "catmullrom",
              "post": [0.0,97.70014953613281,-209.98387145996094]
            },
            "0.333333333333": {
              "lerp_mode": "catmullrom",
              "post": [0.0,110.33091735839844,-199.62969970703125]
            },
            "0.366666666667": {
              "lerp_mode": "catmullrom",
              "post": [0.0,89.75126647949219,-225.19752502441406]
            },
            "0.4": {
              "lerp_mode": "catmullrom",
              "post": [0.0,56.24729919433594,-241.80650329589844]
            },
            "0.433333333333": {
              "lerp_mode": "catmullrom",
              "post": [0.0,63.54151916503906,-237.64698791503906]
            },
            "0.466666666667": {
              "lerp_mode": "catmullrom",
              "post": [0.0,77.08795166015625,-229.9221649169922]
            },
            "0.5": {
              "lerp_mode": "catmullrom",
              "post": [0.0,84.38217163085938,-225.7626495361328]
            },
            "0.533333333333": {
              "lerp_mode": "catmullrom",
              "post": [0.0,79.98609924316406,-228.26950073242188]
            },
            "0.566666666667": {
              "lerp_mode": "catmullrom",
              "post": [0.0,70.31472778320312,-233.78457641601562]
            },
            "0.6": {
              "lerp_mode": "catmullrom",
              "post": [0.0,60.64337158203125,-239.29965209960938]
            },
            "0.7": {
              "lerp_mode": "catmullrom",
              "post": [0.0,58.46211242675781,-241.51364135742188]
            },
            "1.4": {
              "lerp_mode": "catmullrom",
              "post": [0.0,56.24729919433594,-241.80650329589844]
            },
            "lod_distance": 0.0
          },
          "rotation": {
            "0.0": {
              "lerp_mode": "catmullrom",
              "post": [0.0,0.0,0.0]
            },
            "0.0333333333333": {
              "lerp_mode": "catmullrom",
              "post": [-24.740055084228516,0.0,0.0]
            },
            "0.0666666666667": {
              "lerp_mode": "catmullrom",
              "post": [-79.7672119140625,0.0,0.0]
            },
            "0.1": {
              "lerp_mode": "catmullrom",
              "post": [-136.29196166992188,0.0,0.0]
            },
            "0.133333333333": {
              "lerp_mode": "catmullrom",
              "post": [-165.52481079101562,0.0,0.0]
            },
            "0.166666666667": {
              "lerp_mode": "catmullrom",
              "post": [-169.7402801513672,0.0,0.0]
            },
            "0.233333333333": {
              "lerp_mode": "catmullrom",
              "post": [-171.51519775390625,0.0,0.0]
            },
            "0.266666666667": {
              "lerp_mode": "catmullrom",
              "post": [-163.78916931152344,0.0,0.0]
            },
            "0.3": {
              "lerp_mode": "catmullrom",
              "post": [-149.44082641601562,0.0,0.0]
            },
            "0.333333333333": {
              "lerp_mode": "catmullrom",
              "post": [-141.7147979736328,0.0,0.0]
            },
            "0.366666666667": {
              "lerp_mode": "catmullrom",
              "post": [-157.87948608398438,0.0,0.0]
            },
            "0.4": {
              "lerp_mode": "catmullrom",
              "post": [-174.044189453125,0.0,0.0]
            },
            "0.433333333333": {
              "lerp_mode": "catmullrom",
              "post": [-170.0191650390625,0.0,0.0]
            },
            "0.5": {
              "lerp_mode": "catmullrom",
              "post": [-158.5190887451172,0.0,0.0]
            },
            "0.6": {
              "lerp_mode": "catmullrom",
              "post": [-171.61839294433594,0.0,0.0]
            },
            "0.7": {
              "lerp_mode": "catmullrom",
              "post": [-172.87612915039062,0.0,0.0]
            },
            "1.4": {
              "lerp_mode": "catmullrom",
              "post": [-174.044189453125,0.0,0.0]
            },
            "lod_distance": 0.0
          }
        },
        "joint_root_m": {
          "lod_distance": 0.0,
          "position": {
            "0.0": {
              "lerp_mode": "catmullrom",
              "post": [-3.469446951953614e-18,3.159361839294432,2.7122039794921875]
            },
            "0.0333333333333": {
              "lerp_mode": "catmullrom",
              "post": [3.460594878628378e-18,1.118258833885191,153.8971710205078]
            },
            "0.0666666666667": {
              "lerp_mode": "catmullrom",
              "post": [0.0,-0.9228441119194047,245.86851501464844]
            },
            "0.1": {
              "lerp_mode": "catmullrom",
              "post": [1.734723475976807e-18,-0.7811110019683855,251.67698669433594]
            },
            "0.166666666667": {
              "lerp_mode": "catmullrom",
              "post": [-8.731748531406965e-19,0.08420673012733292,255.53453063964844]
            },
            "0.233333333333": {
              "lerp_mode": "catmullrom",
              "post": [-6.281464815120495e-19,1.128555774688719,253.2334442138672]
            },
            "0.266666666667": {
              "lerp_mode": "catmullrom",
              "post": [-8.520842571332584e-23,1.4940779209136945,234.37904357910156]
            },
            "0.3": {
              "lerp_mode": "catmullrom",
              "post": [0.0,1.635810971260069,199.18373107910156]
            },
            "0.333333333333": {
              "lerp_mode": "catmullrom",
              "post": [0.0,0.0,0.0]
            },
            "0.366666666667": {
              "lerp_mode": "catmullrom",
              "post": [0.0,0.0,0.0]
            },
            "0.4": {
              "lerp_mode": "catmullrom",
              "post": [0.0,0.0,0.0]
            },
            "0.5": {
              "lerp_mode": "catmullrom",
              "post": [0.0,0.0,0.0]
            },
            "0.7": {
              "lerp_mode": "catmullrom",
              "post": [0.0,0.0,0.0]
            },
            "1.4": {
              "lerp_mode": "catmullrom",
              "post": [0.0,0.0,0.0]
            },
            "lod_distance": 0.0
          },
          "rotation": {
            "0.0": {
              "lerp_mode": "catmullrom",
              "post": [0.007720947265625,0.7170692086219788,-0.00135040283203125]
            },
            "0.0333333333333": {
              "lerp_mode": "catmullrom",
              "post": [0.0059967041015625,0.999396800994873,-0.0011444091796875]
            },
            "0.0666666666667": {
              "lerp_mode": "catmullrom",
              "post": [0.00385284423828125,1.0397292375564575,-0.0008544921875]
            },
            "0.1": {
              "lerp_mode": "catmullrom",
              "post": [0.0030059814453125,1.0003225803375244,-0.000701904296875]
            },
            "0.133333333333": {
              "lerp_mode": "catmullrom",
              "post": [0.00222015380859375,0.8942278027534485,-0.0005340576171875]
            },
            "0.166666666667": {
              "lerp_mode": "catmullrom",
              "post": [0.00150299072265625,0.7396324872970581,-0.00037384033203125]
            },
            "0.2": {
              "lerp_mode": "catmullrom",
              "post": [0.000885009765625,0.554724395275116,-0.0002288818359375]
            },
            "0.233333333333": {
              "lerp_mode": "catmullrom",
              "post": [0.0004119873046875,0.35769110918045044,-0.0001068115234375]
            },
            "0.266666666667": {
              "lerp_mode": "catmullrom",
              "post": [0.00011444091796875,0.1667204350233078,-3.0517578125e-05]
            },
            "0.3": {
              "lerp_mode": "catmullrom",
              "post": [0.0,0.0,0.0]
            },
            "0.333333333333": {
              "lerp_mode": "catmullrom",
              "post": [0.0,0.0,0.0]
            },
            "0.366666666667": {
              "lerp_mode": "catmullrom",
              "post": [0.0,0.0,0.0]
            },
            "0.4": {
              "lerp_mode": "catmullrom",
              "post": [0.0,0.0,0.0]
            },
            "0.5": {
              "lerp_mode": "catmullrom",
              "post": [0.0,0.0,0.0]
            },
            "0.7": {
              "lerp_mode": "catmullrom",
              "post": [0.0,0.0,0.0]
            },
            "1.4": {
              "lerp_mode": "catmullrom",
              "post": [0.0,0.0,0.0]
            },
            "lod_distance": 0.0
          }
        }
      },
      "loop": "hold_last_frame",
      "particle_effects": {
        "0.1":  [
          {
            "bind_to_actor": false,
            "effect": "fx_open",
            "enabled": true,
            "locator": "loc_fx_open"
          },
          {
            "effect": "fx_trail",
            "enabled": true,
            "locator": "loc_fx_open"
          }
        ],
        "0.333":  [
          {
            "bind_to_actor": false,
            "effect": "fx_land",
            "enabled": true,
            "locator": "loc_fx_main"
          }
        ]
      },
      "sound_effects": {
        "0.01":  [
          {
            "effect": "open",
            "enabled": true
          }
        ],
        "0.4":  [
          {
            "effect": "crate_lp_stop",
            "enabled": true
          }
        ]
      },
      "timeline": {
        "2.20000004768372": ["variable.change_material = 1;","variable.is_light = 0;"]
      }
    }
  }
}
